MANIFEST.in
README.txt
setup.cfg
setup.py
docs/HISTORY.txt
docs/INSTALL.txt
docs/LICENSE.GPL
docs/LICENSE.txt
enslyon/__init__.py
enslyon.opdsshowroom.egg-info/PKG-INFO
enslyon.opdsshowroom.egg-info/SOURCES.txt
enslyon.opdsshowroom.egg-info/dependency_links.txt
enslyon.opdsshowroom.egg-info/entry_points.txt
enslyon.opdsshowroom.egg-info/namespace_packages.txt
enslyon.opdsshowroom.egg-info/not-zip-safe
enslyon.opdsshowroom.egg-info/paster_plugins.txt
enslyon.opdsshowroom.egg-info/requires.txt
enslyon.opdsshowroom.egg-info/top_level.txt
enslyon/opdsshowroom/INTEGRATION.txt
enslyon/opdsshowroom/LibraryShowroom.txt
enslyon/opdsshowroom/__init__.py
enslyon/opdsshowroom/configure.zcml
enslyon/opdsshowroom/library_showroom.py
enslyon/opdsshowroom/tests.py
enslyon/opdsshowroom/library_showroom_templates/showroomview.pt
enslyon/opdsshowroom/locales/README.txt
enslyon/opdsshowroom/locales/enslyon.opdsshowroom.pot
enslyon/opdsshowroom/locales/en/LC_MESSAGES/enslyon.opdsshowroom.mo
enslyon/opdsshowroom/locales/en/LC_MESSAGES/enslyon.opdsshowroom.po
enslyon/opdsshowroom/locales/fr/LC_MESSAGES/enslyon.opdsshowroom.mo
enslyon/opdsshowroom/locales/fr/LC_MESSAGES/enslyon.opdsshowroom.po
enslyon/opdsshowroom/models/library_showroom.xml
enslyon/opdsshowroom/profiles/default/metadata.xml
enslyon/opdsshowroom/profiles/default/types.xml
enslyon/opdsshowroom/profiles/default/types/enslyon.opdsshowroom.libraryshowroom.xml
enslyon/opdsshowroom/resources/README.txt