Metadata-Version: 1.1
Name: enslyon.opdsshowroom
Version: 1.0.2
Summary: Showroom for OPDS Feed
Home-page: https://github.com/collective/enslyon.opdsshowroom
Author: Encolpe DEGOUTE
Author-email: encolpe@colpi.org
License: GPL
Keywords: Plone plone rest REST OPDS opds
Platform: UNKNOWN
Classifier: Environment :: Web Environment
Classifier: Framework :: Plone
Classifier: Framework :: Plone :: 5.0
Classifier: Framework :: Plone :: 4.3
Classifier: Programming Language :: Python
Classifier: Programming Language :: Python :: 2.7
Classifier: Operating System :: OS Independent
Classifier: License :: OSI Approved :: GNU General Public License v2 (GPLv2)
